topsis_divye_rollnumber/__init__.py
topsis_divye_rollnumber/topsis.py
topsis_divye_rollnumber-1.0.1.dist-info/METADATA
topsis_divye_rollnumber-1.0.1.dist-info/WHEEL
topsis_divye_rollnumber-1.0.1.dist-info/entry_points.txt
topsis_divye_rollnumber-1.0.1.dist-info/top_level.txt
topsis_divye_rollnumber-1.0.1.dist-info/RECORD
