Metadata-Version: 2.4
Name: Topsis-Divye-ROLLNUMBER
Version: 1.0.1
Requires-Dist: pandas
Requires-Dist: numpy
Dynamic: requires-dist
